sms_api_guru/__init__.py
sms_api_guru-0.0.2.dist-info/METADATA
sms_api_guru-0.0.2.dist-info/WHEEL
sms_api_guru-0.0.2.dist-info/licenses/LICENSE
sms_api_guru-0.0.2.dist-info/RECORD
